pykeedy/__init__.py
pykeedy/analysis.py
pykeedy/analyze.py
pykeedy/crypt.py
pykeedy/data/__init__.py
pykeedy/data/encodings/greshko.yaml
pykeedy/data/font/Fairfax/FairfaxEVAHD.eot
pykeedy/data/font/Fairfax/FairfaxEVAHD.ttf
pykeedy/data/font/Fairfax/FairfaxV101HD.eot
pykeedy/data/font/Fairfax/FairfaxV101HD.ttf
pykeedy/data/font/Fairfax/OFL.txt
pykeedy/data/font/Mappings/EVA.TXT
pykeedy/data/font/Mappings/V101.TXT
pykeedy/data/font/Voynich/VoynichEVA.eot
pykeedy/data/font/Voynich/VoynichEVA.ttf
pykeedy/data/font/Voynich/VoynichUnicode.eot
pykeedy/data/font/Voynich/VoynichUnicode.ttf
pykeedy/data/font/Voynich/VoynichV101.eot
pykeedy/data/font/Voynich/VoynichV101.ttf
pykeedy/data/plaintexts/inferno.txt
pykeedy/data/plaintexts/info
pykeedy/data/plaintexts/meidekranz.txt
pykeedy/data/plaintexts/naturalis.txt
pykeedy/data/transliterations/RF1b-e.txt
pykeedy/data/transliterations/RF1b-er.txt
pykeedy/datastructures.py
pykeedy/naibbe.py
pykeedy/parse_analysis.py
pykeedy/run_test.py
pykeedy/slots.py
pykeedy/utils.py
pykeedy-0.1.1.data/data/__init__.py
pykeedy-0.1.1.data/data/encodings/greshko.yaml
pykeedy-0.1.1.data/data/font/Fairfax/FairfaxEVAHD.eot
pykeedy-0.1.1.data/data/font/Fairfax/FairfaxEVAHD.ttf
pykeedy-0.1.1.data/data/font/Fairfax/FairfaxV101HD.eot
pykeedy-0.1.1.data/data/font/Fairfax/FairfaxV101HD.ttf
pykeedy-0.1.1.data/data/font/Fairfax/OFL.txt
pykeedy-0.1.1.data/data/font/Mappings/EVA.TXT
pykeedy-0.1.1.data/data/font/Mappings/V101.TXT
pykeedy-0.1.1.data/data/font/Voynich/VoynichEVA.eot
pykeedy-0.1.1.data/data/font/Voynich/VoynichEVA.ttf
pykeedy-0.1.1.data/data/font/Voynich/VoynichUnicode.eot
pykeedy-0.1.1.data/data/font/Voynich/VoynichUnicode.ttf
pykeedy-0.1.1.data/data/font/Voynich/VoynichV101.eot
pykeedy-0.1.1.data/data/font/Voynich/VoynichV101.ttf
pykeedy-0.1.1.data/data/plaintexts/inferno.txt
pykeedy-0.1.1.data/data/plaintexts/info
pykeedy-0.1.1.data/data/plaintexts/meidekranz.txt
pykeedy-0.1.1.data/data/plaintexts/naturalis.txt
pykeedy-0.1.1.dist-info/WHEEL
pykeedy-0.1.1.dist-info/METADATA
pykeedy-0.1.1.dist-info/RECORD
