Metadata-Version: 2.3
Name: pykeedy
Version: 0.1.1
Summary: Tools for easy statistical analysis of the Voynich Manuscript
Author: Patrick Spencer
Author-email: Patrick Spencer <patrickwspencer@gmail.com>
License: MIT
Classifier: Development Status :: 3 - Alpha
Classifier: Topic :: Text Processing :: Linguistic
Classifier: Programming Language :: Python :: 3.12
Requires-Dist: matplotlib>=3.10.6
Requires-Dist: numpy>=2.3.2
Requires-Dist: pydantic>=2.11.7
Requires-Dist: pyyaml>=6.0.2
Requires-Dist: regex>=2025.8.29
Requires-Python: >=3.12
